batch/__init__.py
batch/batch_transformations.py
streaming/__init__.py
streaming/streaming_transformations.py
ivoy_de-0.0.1.dist-info/METADATA
ivoy_de-0.0.1.dist-info/WHEEL
ivoy_de-0.0.1.dist-info/top_level.txt
ivoy_de-0.0.1.dist-info/RECORD
