Metadata-Version: 2.1
Name: ivoy-de
Version: 0.0.1
Summary: Perform transformations for batch and streaming data
Home-page: UNKNOWN
Author: Carlos Lopez
Author-email: carlos.lopez@ivoy.mx
License: UNKNOWN
Platform: UNKNOWN
